pyflared/__about__.py
pyflared/__init__.py
pyflared/_commands.py
pyflared/_patterns.py
pyflared/cli.py
pyflared/consts.py
pyflared/api_sdk/__init__.py
pyflared/api_sdk/fetch.py
pyflared/api_sdk/monkey_patch.py
pyflared/api_sdk/tunnel_manager.py
pyflared/api_sdk/types.py
pyflared/binary/__init__.py
pyflared/binary/binary_decorator.py
pyflared/binary/process.py
pyflared/log/__init__.py
pyflared/log/config.py
pyflared/log/pretty.py
pyflared/shared/__init__.py
pyflared/shared/contants.py
pyflared/shared/types.py
pyflared/utils/__init__.py
pyflared/utils/async_helper.py
pyflared/bin/cloudflared
pyflared-0.0.1b7.dist-info/METADATA
pyflared-0.0.1b7.dist-info/WHEEL
pyflared-0.0.1b7.dist-info/entry_points.txt
pyflared-0.0.1b7.dist-info/licenses/LICENSE.txt
pyflared-0.0.1b7.dist-info/RECORD
