Metadata-Version: 2.4
Name: pyflared
Version: 0.0.1b7
Summary: A Python CLI tool for effortless Cloudflare Tunnel management
Project-URL: Documentation, https://github.com/AzmainMahatab/pyflared#readme
Project-URL: Issues, https://github.com/AzmainMahatab/pyflared/issues
Project-URL: Source, https://github.com/AzmainMahatab/pyflared
Author-email: Azmain <azmainmahatab012@gmail.com>
License-Expression: MIT
License-File: LICENSE.txt
Classifier: Development Status :: 4 - Beta
Classifier: Programming Language :: Python
Classifier: Programming Language :: Python :: 3.12
Classifier: Programming Language :: Python :: Implementation :: CPython
Classifier: Programming Language :: Python :: Implementation :: PyPy
Requires-Python: >=3.12
Requires-Dist: aiostream
Requires-Dist: beartype
Requires-Dist: cloudflare
Requires-Dist: loguru
Requires-Dist: platformdirs
Requires-Dist: pydantic
Requires-Dist: pydantic-settings
Requires-Dist: rich
Requires-Dist: typer
